familytree/__init__.py
familytree/akhil.py
familytree/bhavani.py
tester/__init__.py
tester/test_akhil.py
tester/test_bhavani.py
familyoccupation-0.0.2.dist-info/METADATA
familyoccupation-0.0.2.dist-info/WHEEL
familyoccupation-0.0.2.dist-info/top_level.txt
familyoccupation-0.0.2.dist-info/RECORD
